littlescribe/__init__.py
littlescribe/__main__.py
littlescribe/littlescribe.py
littlescribe-1.1.1.dist-info/METADATA
littlescribe-1.1.1.dist-info/WHEEL
littlescribe-1.1.1.dist-info/entry_points.txt
littlescribe-1.1.1.dist-info/RECORD
