Metadata-Version: 2.4
Name: littlescribe
Version: 1.1.1
Summary: Real-time audio transcription with AI summarization
Project-URL: Homepage, https://github.com/yourusername/AI-LittleScribe
Project-URL: Repository, https://github.com/yourusername/AI-LittleScribe
Author-email: Nicolas de Place <deplacenicolas@gmail.com>
License: MIT
Keywords: ai,audio,aws,speech-to-text,transcription
Classifier: Development Status :: 4 - Beta
Classifier: Intended Audience :: Developers
Classifier: License :: OSI Approved :: MIT License
Classifier: Programming Language :: Python :: 3
Classifier: Programming Language :: Python :: 3.7
Classifier: Programming Language :: Python :: 3.8
Classifier: Programming Language :: Python :: 3.9
Classifier: Programming Language :: Python :: 3.10
Classifier: Programming Language :: Python :: 3.11
Classifier: Programming Language :: Python :: 3.12
Requires-Python: >=3.7
Requires-Dist: amazon-transcribe
Requires-Dist: boto3
Requires-Dist: numpy
Requires-Dist: pyaudio
